coe/__init__.py
coe/__version__.py
coe/coe.py
coe/message.py
coe/messagebuilder.py
python_can_coe-0.1.2.dist-info/LICENSE.md
python_can_coe-0.1.2.dist-info/METADATA
python_can_coe-0.1.2.dist-info/WHEEL
python_can_coe-0.1.2.dist-info/entry_points.txt
python_can_coe-0.1.2.dist-info/top_level.txt
python_can_coe-0.1.2.dist-info/RECORD
