Metadata-Version: 2.2
Name: python-can-coe
Version: 0.1.2
Summary: An interface introducing CAN over Ethernet into python-can
Author-email: Gerrit Beine <mail@gerritbeine.com>
Maintainer-email: Gerrit Beine <mail@gerritbeine.com>
License: Copyright (c) 2016-2025, Gerrit Beine
Project-URL: Homepage, https://c0d3.sh/smarthome/python-can-coe
Project-URL: Issues, https://github.com/gbeine/python-can-coe/issues
Classifier: Development Status :: 4 - Beta
Classifier: Intended Audience :: Developers
Classifier: License :: OSI Approved :: BSD License
Classifier: Programming Language :: Python :: 3.8
Classifier: Topic :: Home Automation
Classifier: Topic :: Software Development :: Embedded Systems :: Controller Area Network (CAN)
Requires-Python: >=3.8
License-File: LICENSE.md
Requires-Dist: python-can>=4.5.0
